[{
	"magic": 0,
	"luck": 0,
	"strength": 0,
	"ring": "None",
	"startStatus": true,
	"inventory": [
		["None"],
		["None"],
		["None"],
		["None"],
		["None"],
		["None"],
		["None"],
		["None"],
		["None"]
	],
	"hitpoints": 0,
	"balance": 0,
	"helmet": "None",
	"boots": "None",
	"leggings": "None",
	"offHand": "None",
	"chest": "None",
	"clientId": 168545253991645185,
	"durability": 0,
	"necklace": "None",
	"classStatus": false,
	"physicalDefense": 0,
	"dexterity": 0,
	"battleStatus": false,
	"onHand": "None",
	"magicalDefense": 0,
	"location": "Axel_mansion",
	"cape": "None",
	"items": {},
	"classType": "thief"
}]